clash_sub_manager/__init__.py
clash_sub_manager/cli.py
clash_sub_manager/config.py
clash_sub_manager/console.py
clash_sub_manager/proxy_cli.py
clash_sub_manager/proxy_selector.py
clash_sub_manager/subscription_manager.py
clash_sub_manager/data/config.json.sample
clash_subscription_manager-0.6.4.dist-info/METADATA
clash_subscription_manager-0.6.4.dist-info/WHEEL
clash_subscription_manager-0.6.4.dist-info/entry_points.txt
clash_subscription_manager-0.6.4.dist-info/top_level.txt
clash_subscription_manager-0.6.4.dist-info/RECORD
