Metadata-Version: 2.4
Name: clash-subscription-manager
Version: 0.6.4
Summary: A simple tool to manage and update Clash proxy subscriptions
Project-URL: Homepage, https://github.com/kadaliao/clash-subscription-manager
Project-URL: Source, https://github.com/kadaliao/clash-subscription-manager
Project-URL: Tracker, https://github.com/kadaliao/clash-subscription-manager/issues
Classifier: Environment :: Console
Classifier: License :: OSI Approved :: MIT License
Classifier: Programming Language :: Python :: 3
Classifier: Programming Language :: Python :: 3.9
Classifier: Programming Language :: Python :: 3.10
Classifier: Programming Language :: Python :: 3.11
Classifier: Programming Language :: Python :: 3.12
Requires-Python: >=3.9
Requires-Dist: requests>=2.31.0
Requires-Dist: pyyaml>=6.0
